softlab/VERSION.txt
softlab/__init__.py
softlab/_version.py
softlab/huo/__init__.py
softlab/huo/process/__init__.py
softlab/huo/process/common.py
softlab/huo/process/composite.py
softlab/huo/process/process.py
softlab/huo/process/simple.py
softlab/huo/scheduler/__init__.py
softlab/huo/scheduler/impl_scheduler.py
softlab/huo/scheduler/scheduler.py
softlab/jin/__init__.py
softlab/jin/dp/__init__.py
softlab/jin/misc/__init__.py
softlab/jin/misc/data_manipulator.py
softlab/jin/misc/delegated.py
softlab/jin/misc/limited_attribute.py
softlab/jin/misc/print_helper.py
softlab/jin/sp/__init__.py
softlab/jin/sp/base.py
softlab/jin/sp/common.py
softlab/jin/sp/iq_modulation.py
softlab/jin/sp/noise.py
softlab/jin/sp/operate.py
softlab/jin/sp/window.py
softlab/jin/validator/__init__.py
softlab/jin/validator/implements.py
softlab/jin/validator/validator.py
softlab/jin/vis/__init__.py
softlab/jin/vis/plot.py
softlab/mu/__init__.py
softlab/mu/cli/__init__.py
softlab/mu/notebooks/__init__.py
softlab/mu/notebooks/file_selector.py
softlab/mu/notebooks/interactive.py
softlab/mu/server/__init__.py
softlab/mu/services/__init__.py
softlab/shui/__init__.py
softlab/shui/backend.py
softlab/shui/data/__init__.py
softlab/shui/data/backend.py
softlab/shui/data/base.py
softlab/shui/data/io.py
softlab/shui/profile/__init__.py
softlab/shui/profile/base.py
softlab/shui/profile/manage.py
softlab/shui/profile/backend/__init__.py
softlab/shui/profile/backend/base.py
softlab/shui/profile/backend/getter.py
softlab/shui/profile/backend/json_profile.py
softlab/shui/profile/backend/memory.py
softlab/tu/__init__.py
softlab/tu/station/__init__.py
softlab/tu/station/device.py
softlab/tu/station/parameter.py
softlab/tu/station/station.py
softlab/tu/station/visa.py
softlab/tu/theory/__init__.py
softlab/tu/theory/mapping.py
softlab/tu/theory/model.py
softlab-0.3.0.dist-info/LICENSE
softlab-0.3.0.dist-info/METADATA
softlab-0.3.0.dist-info/WHEEL
softlab-0.3.0.dist-info/top_level.txt
softlab-0.3.0.dist-info/RECORD
