Metadata-Version: 2.1
Name: softlab
Version: 0.3.0
Summary: Toolkit to build software-defined laboratory
Author-email: Edward Chou <prettyage.new@gmail.com>
License: MIT
Project-URL: Homepage, https://github.com/hoolheart/softlab
Keywords: science,laboratory,toolkit
Classifier: Environment :: Console
Classifier: Intended Audience :: Developers
Classifier: Intended Audience :: Science/Research
Classifier: License :: OSI Approved :: MIT License
Classifier: Operating System :: MacOS
Classifier: Operating System :: Microsoft :: Windows
Classifier: Operating System :: POSIX :: Linux
Classifier: Programming Language :: Python :: 3.7
Classifier: Programming Language :: Python :: 3.8
Classifier: Programming Language :: Python :: 3.9
Classifier: Programming Language :: Python :: 3.10
Classifier: Programming Language :: Python :: 3.11
Classifier: Topic :: Scientific/Engineering
Requires-Python: >=3.7
License-File: LICENSE
Requires-Dist: matplotlib
Requires-Dist: plotly
Requires-Dist: numpy
Requires-Dist: scipy
Requires-Dist: pandas
Requires-Dist: imageio
Requires-Dist: ipywidgets
Requires-Dist: pyvisa
Requires-Dist: uuid
Requires-Dist: h5py
Requires-Dist: asyncio
